{"_type":"export","__export_format":4,"__export_date":"2023-01-11T00:25:02.906Z","__export_source":"insomnia.desktop.app:v2022.7.0","resources":[{"_id":"req_822449da73cc4344a3ec2aac797f30a1","parentId":"wrk_da667a3480c649449d6ebea17eec9829","modified":1673396603075,"created":1673396416979,"url":"{{ _.BASE_URL }}/shipments","name":"POST shipment","description":"","method":"POST","body":{"mimeType":"application/json","text":"{\n\t\"productId\": 141284,\n\t\"name\": \"idk\",\n\t\"addr\": \"123 rithm st\",\n\t\"zip\": \"43643\"\n}"},"parameters":[],"headers":[{"name":"Content-Type","value":"application/json"}],"authentication":{},"metaSortKey":-1673396416979,"isPrivate":false,"settingStoreCookies":true,"settingSendCookies":true,"settingDisableRenderRequestBody":false,"settingEncodeUrl":true,"settingRebuildPath":true,"settingFollowRedirects":"global","_type":"request"},{"_id":"wrk_da667a3480c649449d6ebea17eec9829","parentId":null,"modified":1673396415789,"created":1673396415789,"name":"Express Shipping","description":"","scope":"collection","_type":"workspace"},{"_id":"env_3f7494387f55038c5aca017b128f83d39fef2031","parentId":"wrk_da667a3480c649449d6ebea17eec9829","modified":1673396430333,"created":1673396415791,"name":"Base Environment","data":{"BASE_URL":"http://localhost:3000"},"dataPropertyOrder":{"&":["BASE_URL"]},"color":null,"isPrivate":false,"metaSortKey":1673396415791,"_type":"environment"},{"_id":"jar_3f7494387f55038c5aca017b128f83d39fef2031","parentId":"wrk_da667a3480c649449d6ebea17eec9829","modified":1673396415792,"created":1673396415792,"name":"Default Jar","cookies":[],"_type":"cookie_jar"},{"_id":"spc_1b6fd976e8274c5dab4a098b870d7072","parentId":"wrk_da667a3480c649449d6ebea17eec9829","modified":1673396415790,"created":1673396415790,"fileName":"Express Shipping","contents":"","contentType":"yaml","_type":"api_spec"}]}